{
    "customizations": [
        {
            "section": "Men",
            "items": "Jeans",
            "tag": [
                {
                    "name": "Pocket",
                    "images": []
                },
                {
                    "name": "Fit",
                    "images": []
                }
            ]
        },
        {
            "section": "Men",
            "items": "Polo Shirt",
            "tag": [
                {
                    "name": "Collar",
                    "images": [
                        "https://drive.google.com/file/d/1rKdQRGilxwNMPutwN2AdE_GOMvbLnxlH/view?usp=sharing",
                        "https://drive.google.com/file/d/1Lch6qpkxr4MFwpThlR7Yj7ivhO60UrP5/view?usp=sharing",
                        "https://drive.google.com/file/d/1G62fAz1UnrPdz_jOyZsp_ee1imsnonQ2/view?usp=sharing",
                        "https://drive.google.com/file/d/1XQXkssYLf_QKvTED1Qsd7xeeOjp7ar_3/view?usp=sharing"
                    ]
                },
                {
                    "name": "Front",
                    "images": []
                },
                {
                    "name": "Back",
                    "images": []
                },
                {
                    "name": "Sleeves",
                    "images": []
                }
            ]
        },
        {
            "section": "Women",
            "items": "Shorts",
            "tag": [
                {
                    "name": "Bottom",
                    "images": []
                }
            ]
        },
        {
            "section": "Women",
            "items": "T-Shirt",
            "tag": [
                {
                    "name": "Neck",
                    "images": []
                },
                {
                    "name": "Sleeves",
                    "images": []
                },
                {
                    "name": "Border",
                    "images": []
                }
            ]
        },
        {
            "section": "Women",
            "items": "Blazers",
            "tag": [
                {
                    "name": "Cuffs",
                    "images": [
                        "https://drive.google.com/file/d/1fKWPeouV2RZi6VnCPKvXsel9KZ1VkWG-/view?usp=sharing",
                        "https://drive.google.com/file/d/1m2GWq4C_oFJFbXWAkx91JIAOQEPWEJyz/view?usp=sharing"
                    ]
                },
                {
                    "name": "Collar",
                    "images": [
                        "https://drive.google.com/file/d/1va_pOBafoUr7KDlCcgZe3yuOUswj7HB2/view?usp=sharing",
                        "https://drive.google.com/file/d/1moxGsGyruBHuiNT3-2qTkagUSsGLpPFg/view?usp=sharing",
                        "https://drive.google.com/file/d/18MFB1HwgsbjP08nh1L7meeSUZTaNdlNY/view?usp=sharing"
                    ]
                },
                {
                    "name": "Front",
                    "images": []
                },
                {
                    "name": "Back",
                    "images": []
                },
                {
                    "name": "Pocket",
                    "images": []
                }
            ]
        },
        {
            "section": "Women",
            "items": "Shirts",
            "tag": [
                {
                    "name": "Collars",
                    "images": [
                        "https://drive.google.com/file/d/1RRkIu5iHg-6OUpw3ZDzXSp6CBZ2G1Bb6/view?usp=sharing",
                        "https://drive.google.com/file/d/1SjyAUUaZAzK6oqvacXdIeqjTAikjHKQU/view?usp=sharing",
                        "https://drive.google.com/file/d/1jitZlyCbxwiWFf4R96OoXPHqs-ZH1ZAM/view?usp=sharing"
                    ]
                },
                {
                    "name": "Cuffs",
                    "images": [
                        "https://drive.google.com/file/d/1JSMaJsFvWpK88g1ssqm3WdpV7Nq73bw9/view?usp=sharing",
                        "https://drive.google.com/file/d/1941Va-hkvs2Vqyw9zfPMs1pNSlh3K76b/view?usp=sharing",
                        "https://drive.google.com/file/d/1H9J0n8xgUhIhGS_CFWjv1WtKuTJ_mv1l/view?usp=sharing"
                    ]
                },
                {
                    "name": "Front",
                    "images": []
                },
                {
                    "name": "Back",
                    "images": []
                },
                {
                    "name": "Pocket",
                    "images": []
                }
            ]
        },
        {
            "section": "Kids",
            "items": "Frock",
            "tag": [
                {
                    "name": "Layers",
                    "images": []
                },
                {
                    "name": "Sleeves",
                    "images": []
                }
            ]
        },
        {
            "section": "Men",
            "items": "Pants",
            "tag": [
                {
                    "name": "Pocket",
                    "images": []
                },
                {
                    "name": "Front",
                    "images": []
                }
            ]
        }
    ]
}